{
  "image": "image_364_365_heading_90.jpg",
  "class_ids": [
    2,
    86,
    91,
    100,
    109,
    115,
    116,
    117,
    119,
    123,
    127,
    129,
    131
  ],
  "class_names": [
    "car",
    "door-stuff",
    "house",
    "road",
    "wall-brick",
    "window-other",
    "tree-merged",
    "fence-merged",
    "sky-other-merged",
    "pavement-merged",
    "paper-merged",
    "building-other-merged",
    "wall-other-merged"
  ],
  "regions": [
    {
      "class_id": 2,
      "class_name": "car",
      "bbox": [
        342,
        259,
        398,
        297
      ]
    },
    {
      "class_id": 86,
      "class_name": "door-stuff",
      "bbox": [
        173,
        264,
        206,
        338
      ]
    },
    {
      "class_id": 91,
      "class_name": "house",
      "bbox": [
        0,
        178,
        211,
        259
      ]
    },
    {
      "class_id": 100,
      "class_name": "road",
      "bbox": [
        0,
        251,
        511,
        471
      ]
    },
    {
      "class_id": 109,
      "class_name": "wall-brick",
      "bbox": [
        128,
        276,
        174,
        346
      ]
    },
    {
      "class_id": 115,
      "class_name": "window-other",
      "bbox": [
        146,
        138,
        203,
        183
      ]
    },
    {
      "class_id": 116,
      "class_name": "tree-merged",
      "bbox": [
        0,
        64,
        511,
        323
      ]
    },
    {
      "class_id": 117,
      "class_name": "fence-merged",
      "bbox": [
        116,
        270,
        291,
        349
      ]
    },
    {
      "class_id": 119,
      "class_name": "sky-other-merged",
      "bbox": [
        0,
        0,
        511,
        236
      ]
    },
    {
      "class_id": 123,
      "class_name": "pavement-merged",
      "bbox": [
        0,
        315,
        511,
        359
      ]
    },
    {
      "class_id": 127,
      "class_name": "paper-merged",
      "bbox": [
        59,
        270,
        123,
        318
      ]
    },
    {
      "class_id": 129,
      "class_name": "building-other-merged",
      "bbox": [
        0,
        65,
        511,
        340
      ]
    },
    {
      "class_id": 131,
      "class_name": "wall-other-merged",
      "bbox": [
        0,
        266,
        343,
        348
      ]
    }
  ]
}