{
  "image": "image_362_363_heading_270.jpg",
  "class_ids": [
    0,
    2,
    7,
    13,
    88,
    101,
    116,
    118,
    119,
    123,
    125,
    129,
    131
  ],
  "class_names": [
    "person",
    "car",
    "truck",
    "bench",
    "flower",
    "roof",
    "tree-merged",
    "ceiling-merged",
    "sky-other-merged",
    "pavement-merged",
    "grass-merged",
    "building-other-merged",
    "wall-other-merged"
  ],
  "regions": [
    {
      "class_id": 0,
      "class_name": "person",
      "bbox": [
        439,
        252,
        464,
        303
      ]
    },
    {
      "class_id": 2,
      "class_name": "car",
      "bbox": [
        0,
        265,
        457,
        302
      ]
    },
    {
      "class_id": 7,
      "class_name": "truck",
      "bbox": [
        390,
        296,
        392,
        298
      ]
    },
    {
      "class_id": 13,
      "class_name": "bench",
      "bbox": [
        462,
        281,
        511,
        310
      ]
    },
    {
      "class_id": 88,
      "class_name": "flower",
      "bbox": [
        183,
        425,
        280,
        471
      ]
    },
    {
      "class_id": 101,
      "class_name": "roof",
      "bbox": [
        417,
        87,
        504,
        140
      ]
    },
    {
      "class_id": 116,
      "class_name": "tree-merged",
      "bbox": [
        0,
        0,
        511,
        471
      ]
    },
    {
      "class_id": 118,
      "class_name": "ceiling-merged",
      "bbox": [
        378,
        124,
        480,
        231
      ]
    },
    {
      "class_id": 119,
      "class_name": "sky-other-merged",
      "bbox": [
        160,
        0,
        329,
        198
      ]
    },
    {
      "class_id": 123,
      "class_name": "pavement-merged",
      "bbox": [
        0,
        314,
        511,
        471
      ]
    },
    {
      "class_id": 125,
      "class_name": "grass-merged",
      "bbox": [
        167,
        285,
        511,
        365
      ]
    },
    {
      "class_id": 129,
      "class_name": "building-other-merged",
      "bbox": [
        265,
        230,
        456,
        285
      ]
    },
    {
      "class_id": 131,
      "class_name": "wall-other-merged",
      "bbox": [
        0,
        263,
        390,
        392
      ]
    }
  ]
}