{
  "image": "image_938_939_heading_270.jpg",
  "class_ids": [
    2,
    91,
    100,
    106,
    116,
    119,
    123,
    126,
    129
  ],
  "class_names": [
    "car",
    "house",
    "road",
    "stairs",
    "tree-merged",
    "sky-other-merged",
    "pavement-merged",
    "dirt-merged",
    "building-other-merged"
  ],
  "regions": [
    {
      "class_id": 2,
      "class_name": "car",
      "bbox": [
        0,
        248,
        139,
        415
      ]
    },
    {
      "class_id": 91,
      "class_name": "house",
      "bbox": [
        311,
        270,
        511,
        409
      ]
    },
    {
      "class_id": 100,
      "class_name": "road",
      "bbox": [
        0,
        260,
        376,
        471
      ]
    },
    {
      "class_id": 106,
      "class_name": "stairs",
      "bbox": [
        290,
        271,
        380,
        340
      ]
    },
    {
      "class_id": 116,
      "class_name": "tree-merged",
      "bbox": [
        130,
        0,
        397,
        300
      ]
    },
    {
      "class_id": 119,
      "class_name": "sky-other-merged",
      "bbox": [
        134,
        0,
        346,
        185
      ]
    },
    {
      "class_id": 123,
      "class_name": "pavement-merged",
      "bbox": [
        132,
        269,
        511,
        471
      ]
    },
    {
      "class_id": 126,
      "class_name": "dirt-merged",
      "bbox": [
        190,
        282,
        202,
        289
      ]
    },
    {
      "class_id": 129,
      "class_name": "building-other-merged",
      "bbox": [
        0,
        0,
        511,
        403
      ]
    }
  ]
}