{
  "image": "image_633_634_heading_0.jpg",
  "class_ids": [
    0,
    1,
    2,
    10,
    58,
    90,
    91,
    100,
    116,
    117,
    119,
    122,
    123,
    129
  ],
  "class_names": [
    "person",
    "bicycle",
    "car",
    "fire hydrant",
    "potted plant",
    "gravel",
    "house",
    "road",
    "tree-merged",
    "fence-merged",
    "sky-other-merged",
    "floor-other-merged",
    "pavement-merged",
    "building-other-merged"
  ],
  "regions": [
    {
      "class_id": 0,
      "class_name": "person",
      "bbox": [
        178,
        263,
        185,
        275
      ]
    },
    {
      "class_id": 1,
      "class_name": "bicycle",
      "bbox": [
        0,
        314,
        58,
        365
      ]
    },
    {
      "class_id": 2,
      "class_name": "car",
      "bbox": [
        126,
        258,
        153,
        269
      ]
    },
    {
      "class_id": 10,
      "class_name": "fire hydrant",
      "bbox": [
        49,
        275,
        77,
        325
      ]
    },
    {
      "class_id": 58,
      "class_name": "potted plant",
      "bbox": [
        58,
        194,
        490,
        358
      ]
    },
    {
      "class_id": 90,
      "class_name": "gravel",
      "bbox": [
        0,
        332,
        108,
        471
      ]
    },
    {
      "class_id": 91,
      "class_name": "house",
      "bbox": [
        0,
        0,
        488,
        330
      ]
    },
    {
      "class_id": 100,
      "class_name": "road",
      "bbox": [
        73,
        254,
        417,
        471
      ]
    },
    {
      "class_id": 116,
      "class_name": "tree-merged",
      "bbox": [
        113,
        173,
        468,
        329
      ]
    },
    {
      "class_id": 117,
      "class_name": "fence-merged",
      "bbox": [
        369,
        329,
        488,
        424
      ]
    },
    {
      "class_id": 119,
      "class_name": "sky-other-merged",
      "bbox": [
        21,
        0,
        354,
        218
      ]
    },
    {
      "class_id": 122,
      "class_name": "floor-other-merged",
      "bbox": [
        372,
        396,
        511,
        451
      ]
    },
    {
      "class_id": 123,
      "class_name": "pavement-merged",
      "bbox": [
        0,
        255,
        511,
        471
      ]
    },
    {
      "class_id": 129,
      "class_name": "building-other-merged",
      "bbox": [
        305,
        0,
        511,
        436
      ]
    }
  ]
}