{
  "image": "image_836_837_heading_90.jpg",
  "class_ids": [
    2,
    7,
    86,
    100,
    114,
    115,
    123,
    129,
    131
  ],
  "class_names": [
    "car",
    "truck",
    "door-stuff",
    "road",
    "window-blind",
    "window-other",
    "pavement-merged",
    "building-other-merged",
    "wall-other-merged"
  ],
  "regions": [
    {
      "class_id": 2,
      "class_name": "car",
      "bbox": [
        0,
        218,
        335,
        459
      ]
    },
    {
      "class_id": 7,
      "class_name": "truck",
      "bbox": [
        0,
        217,
        339,
        471
      ]
    },
    {
      "class_id": 86,
      "class_name": "door-stuff",
      "bbox": [
        320,
        267,
        364,
        471
      ]
    },
    {
      "class_id": 100,
      "class_name": "road",
      "bbox": [
        0,
        450,
        349,
        471
      ]
    },
    {
      "class_id": 114,
      "class_name": "window-blind",
      "bbox": [
        0,
        172,
        264,
        224
      ]
    },
    {
      "class_id": 115,
      "class_name": "window-other",
      "bbox": [
        154,
        0,
        287,
        33
      ]
    },
    {
      "class_id": 123,
      "class_name": "pavement-merged",
      "bbox": [
        270,
        398,
        511,
        471
      ]
    },
    {
      "class_id": 129,
      "class_name": "building-other-merged",
      "bbox": [
        0,
        0,
        511,
        471
      ]
    },
    {
      "class_id": 131,
      "class_name": "wall-other-merged",
      "bbox": [
        0,
        0,
        331,
        263
      ]
    }
  ]
}