{
  "image": "image_14_15_heading_180.jpg",
  "class_ids": [
    0,
    2,
    3,
    7,
    24,
    26,
    58,
    91,
    100,
    116,
    117,
    119,
    123,
    129,
    131
  ],
  "class_names": [
    "person",
    "car",
    "motorcycle",
    "truck",
    "backpack",
    "handbag",
    "potted plant",
    "house",
    "road",
    "tree-merged",
    "fence-merged",
    "sky-other-merged",
    "pavement-merged",
    "building-other-merged",
    "wall-other-merged"
  ],
  "regions": [
    {
      "class_id": 0,
      "class_name": "person",
      "bbox": [
        448,
        274,
        505,
        379
      ]
    },
    {
      "class_id": 2,
      "class_name": "car",
      "bbox": [
        404,
        260,
        511,
        327
      ]
    },
    {
      "class_id": 3,
      "class_name": "motorcycle",
      "bbox": [
        210,
        260,
        304,
        345
      ]
    },
    {
      "class_id": 7,
      "class_name": "truck",
      "bbox": [
        504,
        270,
        511,
        273
      ]
    },
    {
      "class_id": 24,
      "class_name": "backpack",
      "bbox": [
        501,
        298,
        508,
        309
      ]
    },
    {
      "class_id": 26,
      "class_name": "handbag",
      "bbox": [
        458,
        302,
        511,
        326
      ]
    },
    {
      "class_id": 58,
      "class_name": "potted plant",
      "bbox": [
        0,
        102,
        434,
        398
      ]
    },
    {
      "class_id": 91,
      "class_name": "house",
      "bbox": [
        446,
        168,
        511,
        245
      ]
    },
    {
      "class_id": 100,
      "class_name": "road",
      "bbox": [
        233,
        313,
        511,
        471
      ]
    },
    {
      "class_id": 116,
      "class_name": "tree-merged",
      "bbox": [
        0,
        128,
        456,
        348
      ]
    },
    {
      "class_id": 117,
      "class_name": "fence-merged",
      "bbox": [
        108,
        339,
        225,
        471
      ]
    },
    {
      "class_id": 119,
      "class_name": "sky-other-merged",
      "bbox": [
        0,
        0,
        511,
        172
      ]
    },
    {
      "class_id": 123,
      "class_name": "pavement-merged",
      "bbox": [
        186,
        284,
        469,
        471
      ]
    },
    {
      "class_id": 129,
      "class_name": "building-other-merged",
      "bbox": [
        0,
        0,
        511,
        471
      ]
    },
    {
      "class_id": 131,
      "class_name": "wall-other-merged",
      "bbox": [
        0,
        137,
        109,
        471
      ]
    }
  ]
}