{
  "image": "image_649_650_heading_0.jpg",
  "class_ids": [
    2,
    7,
    91,
    100,
    116,
    117,
    119,
    123,
    125
  ],
  "class_names": [
    "car",
    "truck",
    "house",
    "road",
    "tree-merged",
    "fence-merged",
    "sky-other-merged",
    "pavement-merged",
    "grass-merged"
  ],
  "regions": [
    {
      "class_id": 2,
      "class_name": "car",
      "bbox": [
        284,
        250,
        511,
        296
      ]
    },
    {
      "class_id": 7,
      "class_name": "truck",
      "bbox": [
        495,
        262,
        495,
        262
      ]
    },
    {
      "class_id": 91,
      "class_name": "house",
      "bbox": [
        0,
        199,
        137,
        297
      ]
    },
    {
      "class_id": 100,
      "class_name": "road",
      "bbox": [
        36,
        262,
        511,
        471
      ]
    },
    {
      "class_id": 116,
      "class_name": "tree-merged",
      "bbox": [
        0,
        0,
        511,
        471
      ]
    },
    {
      "class_id": 117,
      "class_name": "fence-merged",
      "bbox": [
        0,
        247,
        169,
        314
      ]
    },
    {
      "class_id": 119,
      "class_name": "sky-other-merged",
      "bbox": [
        70,
        0,
        511,
        236
      ]
    },
    {
      "class_id": 123,
      "class_name": "pavement-merged",
      "bbox": [
        0,
        310,
        85,
        441
      ]
    },
    {
      "class_id": 125,
      "class_name": "grass-merged",
      "bbox": [
        0,
        239,
        511,
        471
      ]
    }
  ]
}