{
  "image": "image_619_620_heading_270.jpg",
  "class_ids": [
    86,
    100,
    115,
    117,
    123,
    129,
    131
  ],
  "class_names": [
    "door-stuff",
    "road",
    "window-other",
    "fence-merged",
    "pavement-merged",
    "building-other-merged",
    "wall-other-merged"
  ],
  "regions": [
    {
      "class_id": 86,
      "class_name": "door-stuff",
      "bbox": [
        20,
        320,
        23,
        321
      ]
    },
    {
      "class_id": 100,
      "class_name": "road",
      "bbox": [
        0,
        412,
        289,
        471
      ]
    },
    {
      "class_id": 115,
      "class_name": "window-other",
      "bbox": [
        280,
        15,
        511,
        352
      ]
    },
    {
      "class_id": 117,
      "class_name": "fence-merged",
      "bbox": [
        180,
        330,
        511,
        426
      ]
    },
    {
      "class_id": 123,
      "class_name": "pavement-merged",
      "bbox": [
        0,
        322,
        511,
        471
      ]
    },
    {
      "class_id": 129,
      "class_name": "building-other-merged",
      "bbox": [
        0,
        0,
        511,
        404
      ]
    },
    {
      "class_id": 131,
      "class_name": "wall-other-merged",
      "bbox": [
        191,
        375,
        511,
        435
      ]
    }
  ]
}