{
  "image": "image_322_323_heading_90.jpg",
  "class_ids": [
    0,
    1,
    2,
    86,
    100,
    116,
    119,
    123,
    129,
    131
  ],
  "class_names": [
    "person",
    "bicycle",
    "car",
    "door-stuff",
    "road",
    "tree-merged",
    "sky-other-merged",
    "pavement-merged",
    "building-other-merged",
    "wall-other-merged"
  ],
  "regions": [
    {
      "class_id": 0,
      "class_name": "person",
      "bbox": [
        96,
        284,
        147,
        339
      ]
    },
    {
      "class_id": 1,
      "class_name": "bicycle",
      "bbox": [
        85,
        327,
        145,
        377
      ]
    },
    {
      "class_id": 2,
      "class_name": "car",
      "bbox": [
        0,
        274,
        10,
        289
      ]
    },
    {
      "class_id": 86,
      "class_name": "door-stuff",
      "bbox": [
        119,
        275,
        233,
        381
      ]
    },
    {
      "class_id": 100,
      "class_name": "road",
      "bbox": [
        0,
        283,
        155,
        471
      ]
    },
    {
      "class_id": 116,
      "class_name": "tree-merged",
      "bbox": [
        0,
        247,
        18,
        285
      ]
    },
    {
      "class_id": 119,
      "class_name": "sky-other-merged",
      "bbox": [
        0,
        0,
        402,
        212
      ]
    },
    {
      "class_id": 123,
      "class_name": "pavement-merged",
      "bbox": [
        93,
        348,
        331,
        471
      ]
    },
    {
      "class_id": 129,
      "class_name": "building-other-merged",
      "bbox": [
        0,
        0,
        511,
        471
      ]
    },
    {
      "class_id": 131,
      "class_name": "wall-other-merged",
      "bbox": [
        17,
        268,
        463,
        471
      ]
    }
  ]
}