{
  "image": "image_134_135_heading_0.jpg",
  "class_ids": [
    2,
    98,
    109,
    116,
    117,
    123,
    129,
    131
  ],
  "class_names": [
    "car",
    "railroad",
    "wall-brick",
    "tree-merged",
    "fence-merged",
    "pavement-merged",
    "building-other-merged",
    "wall-other-merged"
  ],
  "regions": [
    {
      "class_id": 2,
      "class_name": "car",
      "bbox": [
        168,
        263,
        260,
        299
      ]
    },
    {
      "class_id": 98,
      "class_name": "railroad",
      "bbox": [
        271,
        344,
        511,
        471
      ]
    },
    {
      "class_id": 109,
      "class_name": "wall-brick",
      "bbox": [
        232,
        260,
        352,
        291
      ]
    },
    {
      "class_id": 116,
      "class_name": "tree-merged",
      "bbox": [
        339,
        206,
        511,
        361
      ]
    },
    {
      "class_id": 117,
      "class_name": "fence-merged",
      "bbox": [
        0,
        288,
        511,
        441
      ]
    },
    {
      "class_id": 123,
      "class_name": "pavement-merged",
      "bbox": [
        374,
        340,
        503,
        432
      ]
    },
    {
      "class_id": 129,
      "class_name": "building-other-merged",
      "bbox": [
        0,
        0,
        511,
        314
      ]
    },
    {
      "class_id": 131,
      "class_name": "wall-other-merged",
      "bbox": [
        0,
        274,
        381,
        471
      ]
    }
  ]
}