{
  "image": "image_152_153_heading_0.jpg",
  "class_ids": [
    0,
    1,
    10,
    39,
    74,
    80,
    100,
    119,
    123,
    129
  ],
  "class_names": [
    "person",
    "bicycle",
    "fire hydrant",
    "bottle",
    "clock",
    "banner",
    "road",
    "sky-other-merged",
    "pavement-merged",
    "building-other-merged"
  ],
  "regions": [
    {
      "class_id": 0,
      "class_name": "person",
      "bbox": [
        63,
        243,
        83,
        295
      ]
    },
    {
      "class_id": 1,
      "class_name": "bicycle",
      "bbox": [
        0,
        268,
        436,
        342
      ]
    },
    {
      "class_id": 10,
      "class_name": "fire hydrant",
      "bbox": [
        374,
        277,
        511,
        311
      ]
    },
    {
      "class_id": 39,
      "class_name": "bottle",
      "bbox": [
        214,
        297,
        234,
        334
      ]
    },
    {
      "class_id": 74,
      "class_name": "clock",
      "bbox": [
        434,
        45,
        458,
        63
      ]
    },
    {
      "class_id": 80,
      "class_name": "banner",
      "bbox": [
        222,
        78,
        288,
        97
      ]
    },
    {
      "class_id": 100,
      "class_name": "road",
      "bbox": [
        0,
        304,
        511,
        471
      ]
    },
    {
      "class_id": 119,
      "class_name": "sky-other-merged",
      "bbox": [
        215,
        0,
        511,
        103
      ]
    },
    {
      "class_id": 123,
      "class_name": "pavement-merged",
      "bbox": [
        0,
        300,
        315,
        362
      ]
    },
    {
      "class_id": 129,
      "class_name": "building-other-merged",
      "bbox": [
        0,
        0,
        511,
        327
      ]
    }
  ]
}