{
  "image": "image_195_196_heading_270.jpg",
  "class_ids": [
    91,
    100,
    110,
    115,
    116,
    117,
    119,
    123,
    129
  ],
  "class_names": [
    "house",
    "road",
    "wall-stone",
    "window-other",
    "tree-merged",
    "fence-merged",
    "sky-other-merged",
    "pavement-merged",
    "building-other-merged"
  ],
  "regions": [
    {
      "class_id": 91,
      "class_name": "house",
      "bbox": [
        139,
        0,
        511,
        391
      ]
    },
    {
      "class_id": 100,
      "class_name": "road",
      "bbox": [
        0,
        268,
        284,
        471
      ]
    },
    {
      "class_id": 110,
      "class_name": "wall-stone",
      "bbox": [
        192,
        351,
        400,
        471
      ]
    },
    {
      "class_id": 115,
      "class_name": "window-other",
      "bbox": [
        291,
        0,
        511,
        109
      ]
    },
    {
      "class_id": 116,
      "class_name": "tree-merged",
      "bbox": [
        28,
        212,
        377,
        321
      ]
    },
    {
      "class_id": 117,
      "class_name": "fence-merged",
      "bbox": [
        167,
        276,
        511,
        471
      ]
    },
    {
      "class_id": 119,
      "class_name": "sky-other-merged",
      "bbox": [
        0,
        0,
        262,
        236
      ]
    },
    {
      "class_id": 123,
      "class_name": "pavement-merged",
      "bbox": [
        98,
        271,
        326,
        471
      ]
    },
    {
      "class_id": 129,
      "class_name": "building-other-merged",
      "bbox": [
        0,
        158,
        196,
        325
      ]
    }
  ]
}