{
  "image": "image_444_445_heading_0.jpg",
  "class_ids": [
    91,
    100,
    106,
    116,
    117,
    119,
    123,
    129
  ],
  "class_names": [
    "house",
    "road",
    "stairs",
    "tree-merged",
    "fence-merged",
    "sky-other-merged",
    "pavement-merged",
    "building-other-merged"
  ],
  "regions": [
    {
      "class_id": 91,
      "class_name": "house",
      "bbox": [
        70,
        0,
        404,
        413
      ]
    },
    {
      "class_id": 100,
      "class_name": "road",
      "bbox": [
        165,
        295,
        511,
        471
      ]
    },
    {
      "class_id": 106,
      "class_name": "stairs",
      "bbox": [
        0,
        269,
        195,
        471
      ]
    },
    {
      "class_id": 116,
      "class_name": "tree-merged",
      "bbox": [
        0,
        140,
        511,
        285
      ]
    },
    {
      "class_id": 117,
      "class_name": "fence-merged",
      "bbox": [
        130,
        282,
        415,
        391
      ]
    },
    {
      "class_id": 119,
      "class_name": "sky-other-merged",
      "bbox": [
        0,
        0,
        511,
        198
      ]
    },
    {
      "class_id": 123,
      "class_name": "pavement-merged",
      "bbox": [
        0,
        253,
        415,
        471
      ]
    },
    {
      "class_id": 129,
      "class_name": "building-other-merged",
      "bbox": [
        0,
        0,
        511,
        387
      ]
    }
  ]
}