{
  "image": "image_583_584_heading_180.jpg",
  "class_ids": [
    86,
    91,
    100,
    101,
    115,
    116,
    117,
    119,
    123,
    125,
    129,
    131
  ],
  "class_names": [
    "door-stuff",
    "house",
    "road",
    "roof",
    "window-other",
    "tree-merged",
    "fence-merged",
    "sky-other-merged",
    "pavement-merged",
    "grass-merged",
    "building-other-merged",
    "wall-other-merged"
  ],
  "regions": [
    {
      "class_id": 86,
      "class_name": "door-stuff",
      "bbox": [
        415,
        227,
        511,
        431
      ]
    },
    {
      "class_id": 91,
      "class_name": "house",
      "bbox": [
        140,
        0,
        511,
        433
      ]
    },
    {
      "class_id": 100,
      "class_name": "road",
      "bbox": [
        0,
        273,
        407,
        471
      ]
    },
    {
      "class_id": 101,
      "class_name": "roof",
      "bbox": [
        164,
        107,
        168,
        121
      ]
    },
    {
      "class_id": 115,
      "class_name": "window-other",
      "bbox": [
        416,
        296,
        511,
        433
      ]
    },
    {
      "class_id": 116,
      "class_name": "tree-merged",
      "bbox": [
        0,
        168,
        170,
        300
      ]
    },
    {
      "class_id": 117,
      "class_name": "fence-merged",
      "bbox": [
        0,
        0,
        116,
        192
      ]
    },
    {
      "class_id": 119,
      "class_name": "sky-other-merged",
      "bbox": [
        0,
        0,
        233,
        193
      ]
    },
    {
      "class_id": 123,
      "class_name": "pavement-merged",
      "bbox": [
        161,
        320,
        511,
        471
      ]
    },
    {
      "class_id": 125,
      "class_name": "grass-merged",
      "bbox": [
        0,
        295,
        5,
        299
      ]
    },
    {
      "class_id": 129,
      "class_name": "building-other-merged",
      "bbox": [
        0,
        158,
        511,
        436
      ]
    },
    {
      "class_id": 131,
      "class_name": "wall-other-merged",
      "bbox": [
        118,
        256,
        159,
        320
      ]
    }
  ]
}