{
  "image": "image_526_527_heading_270.jpg",
  "class_ids": [
    2,
    90,
    91,
    100,
    109,
    116,
    119,
    123,
    129,
    131
  ],
  "class_names": [
    "car",
    "gravel",
    "house",
    "road",
    "wall-brick",
    "tree-merged",
    "sky-other-merged",
    "pavement-merged",
    "building-other-merged",
    "wall-other-merged"
  ],
  "regions": [
    {
      "class_id": 2,
      "class_name": "car",
      "bbox": [
        0,
        261,
        263,
        309
      ]
    },
    {
      "class_id": 90,
      "class_name": "gravel",
      "bbox": [
        328,
        384,
        511,
        471
      ]
    },
    {
      "class_id": 91,
      "class_name": "house",
      "bbox": [
        231,
        0,
        497,
        460
      ]
    },
    {
      "class_id": 100,
      "class_name": "road",
      "bbox": [
        0,
        269,
        395,
        471
      ]
    },
    {
      "class_id": 109,
      "class_name": "wall-brick",
      "bbox": [
        323,
        0,
        511,
        462
      ]
    },
    {
      "class_id": 116,
      "class_name": "tree-merged",
      "bbox": [
        157,
        262,
        169,
        287
      ]
    },
    {
      "class_id": 119,
      "class_name": "sky-other-merged",
      "bbox": [
        0,
        0,
        292,
        190
      ]
    },
    {
      "class_id": 123,
      "class_name": "pavement-merged",
      "bbox": [
        0,
        304,
        439,
        471
      ]
    },
    {
      "class_id": 129,
      "class_name": "building-other-merged",
      "bbox": [
        0,
        0,
        421,
        423
      ]
    },
    {
      "class_id": 131,
      "class_name": "wall-other-merged",
      "bbox": [
        349,
        387,
        498,
        460
      ]
    }
  ]
}