{
  "image": "image_655_656_heading_0.jpg",
  "class_ids": [
    0,
    1,
    10,
    56,
    91,
    100,
    115,
    116,
    119,
    123,
    129
  ],
  "class_names": [
    "person",
    "bicycle",
    "fire hydrant",
    "chair",
    "house",
    "road",
    "window-other",
    "tree-merged",
    "sky-other-merged",
    "pavement-merged",
    "building-other-merged"
  ],
  "regions": [
    {
      "class_id": 0,
      "class_name": "person",
      "bbox": [
        343,
        395,
        380,
        459
      ]
    },
    {
      "class_id": 1,
      "class_name": "bicycle",
      "bbox": [
        380,
        360,
        421,
        427
      ]
    },
    {
      "class_id": 10,
      "class_name": "fire hydrant",
      "bbox": [
        132,
        298,
        144,
        331
      ]
    },
    {
      "class_id": 56,
      "class_name": "chair",
      "bbox": [
        326,
        399,
        328,
        401
      ]
    },
    {
      "class_id": 91,
      "class_name": "house",
      "bbox": [
        0,
        201,
        4,
        206
      ]
    },
    {
      "class_id": 100,
      "class_name": "road",
      "bbox": [
        0,
        270,
        385,
        471
      ]
    },
    {
      "class_id": 115,
      "class_name": "window-other",
      "bbox": [
        146,
        0,
        221,
        129
      ]
    },
    {
      "class_id": 116,
      "class_name": "tree-merged",
      "bbox": [
        0,
        173,
        46,
        277
      ]
    },
    {
      "class_id": 119,
      "class_name": "sky-other-merged",
      "bbox": [
        0,
        0,
        476,
        189
      ]
    },
    {
      "class_id": 123,
      "class_name": "pavement-merged",
      "bbox": [
        191,
        343,
        511,
        471
      ]
    },
    {
      "class_id": 129,
      "class_name": "building-other-merged",
      "bbox": [
        27,
        0,
        511,
        436
      ]
    }
  ]
}