{
  "image": "image_428_429_heading_180.jpg",
  "class_ids": [
    2,
    91,
    100,
    116,
    119,
    123,
    129,
    131
  ],
  "class_names": [
    "car",
    "house",
    "road",
    "tree-merged",
    "sky-other-merged",
    "pavement-merged",
    "building-other-merged",
    "wall-other-merged"
  ],
  "regions": [
    {
      "class_id": 2,
      "class_name": "car",
      "bbox": [
        0,
        257,
        511,
        382
      ]
    },
    {
      "class_id": 91,
      "class_name": "house",
      "bbox": [
        12,
        132,
        153,
        316
      ]
    },
    {
      "class_id": 100,
      "class_name": "road",
      "bbox": [
        0,
        274,
        511,
        471
      ]
    },
    {
      "class_id": 116,
      "class_name": "tree-merged",
      "bbox": [
        0,
        0,
        511,
        316
      ]
    },
    {
      "class_id": 119,
      "class_name": "sky-other-merged",
      "bbox": [
        418,
        54,
        511,
        131
      ]
    },
    {
      "class_id": 123,
      "class_name": "pavement-merged",
      "bbox": [
        59,
        299,
        146,
        338
      ]
    },
    {
      "class_id": 129,
      "class_name": "building-other-merged",
      "bbox": [
        0,
        89,
        390,
        304
      ]
    },
    {
      "class_id": 131,
      "class_name": "wall-other-merged",
      "bbox": [
        261,
        282,
        276,
        298
      ]
    }
  ]
}