{
  "image": "image_985_986_heading_180.jpg",
  "class_ids": [
    2,
    100,
    116,
    117,
    119,
    123,
    125,
    126,
    129
  ],
  "class_names": [
    "car",
    "road",
    "tree-merged",
    "fence-merged",
    "sky-other-merged",
    "pavement-merged",
    "grass-merged",
    "dirt-merged",
    "building-other-merged"
  ],
  "regions": [
    {
      "class_id": 2,
      "class_name": "car",
      "bbox": [
        0,
        260,
        511,
        471
      ]
    },
    {
      "class_id": 100,
      "class_name": "road",
      "bbox": [
        0,
        265,
        401,
        471
      ]
    },
    {
      "class_id": 116,
      "class_name": "tree-merged",
      "bbox": [
        0,
        0,
        511,
        390
      ]
    },
    {
      "class_id": 117,
      "class_name": "fence-merged",
      "bbox": [
        209,
        265,
        397,
        313
      ]
    },
    {
      "class_id": 119,
      "class_name": "sky-other-merged",
      "bbox": [
        0,
        0,
        222,
        245
      ]
    },
    {
      "class_id": 123,
      "class_name": "pavement-merged",
      "bbox": [
        374,
        313,
        511,
        380
      ]
    },
    {
      "class_id": 125,
      "class_name": "grass-merged",
      "bbox": [
        502,
        313,
        511,
        336
      ]
    },
    {
      "class_id": 126,
      "class_name": "dirt-merged",
      "bbox": [
        507,
        336,
        511,
        337
      ]
    },
    {
      "class_id": 129,
      "class_name": "building-other-merged",
      "bbox": [
        186,
        120,
        248,
        184
      ]
    }
  ]
}