{
  "image": "image_367_368_heading_270.jpg",
  "class_ids": [
    0,
    2,
    7,
    9,
    80,
    92,
    100,
    116,
    117,
    119,
    123,
    129,
    131
  ],
  "class_names": [
    "person",
    "car",
    "truck",
    "traffic light",
    "banner",
    "light",
    "road",
    "tree-merged",
    "fence-merged",
    "sky-other-merged",
    "pavement-merged",
    "building-other-merged",
    "wall-other-merged"
  ],
  "regions": [
    {
      "class_id": 0,
      "class_name": "person",
      "bbox": [
        0,
        252,
        511,
        318
      ]
    },
    {
      "class_id": 2,
      "class_name": "car",
      "bbox": [
        316,
        267,
        419,
        303
      ]
    },
    {
      "class_id": 7,
      "class_name": "truck",
      "bbox": [
        389,
        249,
        421,
        278
      ]
    },
    {
      "class_id": 9,
      "class_name": "traffic light",
      "bbox": [
        490,
        109,
        511,
        152
      ]
    },
    {
      "class_id": 80,
      "class_name": "banner",
      "bbox": [
        0,
        377,
        57,
        398
      ]
    },
    {
      "class_id": 92,
      "class_name": "light",
      "bbox": [
        55,
        102,
        85,
        126
      ]
    },
    {
      "class_id": 100,
      "class_name": "road",
      "bbox": [
        0,
        252,
        511,
        471
      ]
    },
    {
      "class_id": 116,
      "class_name": "tree-merged",
      "bbox": [
        0,
        228,
        374,
        304
      ]
    },
    {
      "class_id": 117,
      "class_name": "fence-merged",
      "bbox": [
        0,
        282,
        263,
        340
      ]
    },
    {
      "class_id": 119,
      "class_name": "sky-other-merged",
      "bbox": [
        0,
        0,
        511,
        253
      ]
    },
    {
      "class_id": 123,
      "class_name": "pavement-merged",
      "bbox": [
        0,
        272,
        284,
        338
      ]
    },
    {
      "class_id": 129,
      "class_name": "building-other-merged",
      "bbox": [
        0,
        51,
        511,
        303
      ]
    },
    {
      "class_id": 131,
      "class_name": "wall-other-merged",
      "bbox": [
        0,
        282,
        269,
        396
      ]
    }
  ]
}