{
  "image": "image_521_522_heading_180.jpg",
  "class_ids": [
    0,
    2,
    24,
    100,
    116,
    119,
    123,
    125,
    129
  ],
  "class_names": [
    "person",
    "car",
    "backpack",
    "road",
    "tree-merged",
    "sky-other-merged",
    "pavement-merged",
    "grass-merged",
    "building-other-merged"
  ],
  "regions": [
    {
      "class_id": 0,
      "class_name": "person",
      "bbox": [
        21,
        285,
        49,
        339
      ]
    },
    {
      "class_id": 2,
      "class_name": "car",
      "bbox": [
        0,
        262,
        511,
        441
      ]
    },
    {
      "class_id": 24,
      "class_name": "backpack",
      "bbox": [
        46,
        304,
        46,
        312
      ]
    },
    {
      "class_id": 100,
      "class_name": "road",
      "bbox": [
        0,
        244,
        511,
        471
      ]
    },
    {
      "class_id": 116,
      "class_name": "tree-merged",
      "bbox": [
        308,
        235,
        388,
        295
      ]
    },
    {
      "class_id": 119,
      "class_name": "sky-other-merged",
      "bbox": [
        148,
        0,
        511,
        245
      ]
    },
    {
      "class_id": 123,
      "class_name": "pavement-merged",
      "bbox": [
        0,
        284,
        235,
        347
      ]
    },
    {
      "class_id": 125,
      "class_name": "grass-merged",
      "bbox": [
        339,
        292,
        344,
        295
      ]
    },
    {
      "class_id": 129,
      "class_name": "building-other-merged",
      "bbox": [
        0,
        0,
        511,
        291
      ]
    }
  ]
}