{
  "image": "image_37_38_heading_270.jpg",
  "class_ids": [
    91,
    100,
    116,
    119,
    123,
    129,
    131
  ],
  "class_names": [
    "house",
    "road",
    "tree-merged",
    "sky-other-merged",
    "pavement-merged",
    "building-other-merged",
    "wall-other-merged"
  ],
  "regions": [
    {
      "class_id": 91,
      "class_name": "house",
      "bbox": [
        246,
        381,
        256,
        395
      ]
    },
    {
      "class_id": 100,
      "class_name": "road",
      "bbox": [
        197,
        278,
        337,
        471
      ]
    },
    {
      "class_id": 116,
      "class_name": "tree-merged",
      "bbox": [
        320,
        239,
        348,
        268
      ]
    },
    {
      "class_id": 119,
      "class_name": "sky-other-merged",
      "bbox": [
        203,
        0,
        427,
        214
      ]
    },
    {
      "class_id": 123,
      "class_name": "pavement-merged",
      "bbox": [
        239,
        285,
        511,
        471
      ]
    },
    {
      "class_id": 129,
      "class_name": "building-other-merged",
      "bbox": [
        0,
        0,
        511,
        471
      ]
    },
    {
      "class_id": 131,
      "class_name": "wall-other-merged",
      "bbox": [
        0,
        0,
        315,
        471
      ]
    }
  ]
}