{
  "image": "image_980_981_heading_180.jpg",
  "class_ids": [
    109,
    119,
    123,
    124,
    125,
    126,
    131
  ],
  "class_names": [
    "wall-brick",
    "sky-other-merged",
    "pavement-merged",
    "mountain-merged",
    "grass-merged",
    "dirt-merged",
    "wall-other-merged"
  ],
  "regions": [
    {
      "class_id": 109,
      "class_name": "wall-brick",
      "bbox": [
        0,
        69,
        511,
        391
      ]
    },
    {
      "class_id": 119,
      "class_name": "sky-other-merged",
      "bbox": [
        0,
        0,
        511,
        210
      ]
    },
    {
      "class_id": 123,
      "class_name": "pavement-merged",
      "bbox": [
        158,
        301,
        511,
        471
      ]
    },
    {
      "class_id": 124,
      "class_name": "mountain-merged",
      "bbox": [
        505,
        193,
        511,
        196
      ]
    },
    {
      "class_id": 125,
      "class_name": "grass-merged",
      "bbox": [
        0,
        288,
        449,
        471
      ]
    },
    {
      "class_id": 126,
      "class_name": "dirt-merged",
      "bbox": [
        415,
        349,
        435,
        360
      ]
    },
    {
      "class_id": 131,
      "class_name": "wall-other-merged",
      "bbox": [
        0,
        82,
        511,
        393
      ]
    }
  ]
}