{
  "image": "image_508_509_heading_0.jpg",
  "class_ids": [
    0,
    2,
    10,
    100,
    116,
    117,
    119,
    123,
    129,
    131
  ],
  "class_names": [
    "person",
    "car",
    "fire hydrant",
    "road",
    "tree-merged",
    "fence-merged",
    "sky-other-merged",
    "pavement-merged",
    "building-other-merged",
    "wall-other-merged"
  ],
  "regions": [
    {
      "class_id": 0,
      "class_name": "person",
      "bbox": [
        268,
        270,
        278,
        292
      ]
    },
    {
      "class_id": 2,
      "class_name": "car",
      "bbox": [
        0,
        261,
        399,
        373
      ]
    },
    {
      "class_id": 10,
      "class_name": "fire hydrant",
      "bbox": [
        463,
        281,
        479,
        328
      ]
    },
    {
      "class_id": 100,
      "class_name": "road",
      "bbox": [
        0,
        258,
        511,
        471
      ]
    },
    {
      "class_id": 116,
      "class_name": "tree-merged",
      "bbox": [
        0,
        0,
        511,
        283
      ]
    },
    {
      "class_id": 117,
      "class_name": "fence-merged",
      "bbox": [
        399,
        257,
        511,
        301
      ]
    },
    {
      "class_id": 119,
      "class_name": "sky-other-merged",
      "bbox": [
        0,
        0,
        418,
        244
      ]
    },
    {
      "class_id": 123,
      "class_name": "pavement-merged",
      "bbox": [
        261,
        279,
        511,
        354
      ]
    },
    {
      "class_id": 129,
      "class_name": "building-other-merged",
      "bbox": [
        180,
        38,
        511,
        309
      ]
    },
    {
      "class_id": 131,
      "class_name": "wall-other-merged",
      "bbox": [
        0,
        254,
        511,
        319
      ]
    }
  ]
}