{
  "image": "image_608_609_heading_90.jpg",
  "class_ids": [
    0,
    2,
    7,
    92,
    100,
    116,
    117,
    119,
    123,
    129
  ],
  "class_names": [
    "person",
    "car",
    "truck",
    "light",
    "road",
    "tree-merged",
    "fence-merged",
    "sky-other-merged",
    "pavement-merged",
    "building-other-merged"
  ],
  "regions": [
    {
      "class_id": 0,
      "class_name": "person",
      "bbox": [
        38,
        258,
        414,
        315
      ]
    },
    {
      "class_id": 2,
      "class_name": "car",
      "bbox": [
        0,
        254,
        511,
        293
      ]
    },
    {
      "class_id": 7,
      "class_name": "truck",
      "bbox": [
        460,
        256,
        467,
        274
      ]
    },
    {
      "class_id": 92,
      "class_name": "light",
      "bbox": [
        118,
        82,
        151,
        111
      ]
    },
    {
      "class_id": 100,
      "class_name": "road",
      "bbox": [
        0,
        273,
        511,
        471
      ]
    },
    {
      "class_id": 116,
      "class_name": "tree-merged",
      "bbox": [
        0,
        92,
        511,
        298
      ]
    },
    {
      "class_id": 117,
      "class_name": "fence-merged",
      "bbox": [
        194,
        267,
        233,
        277
      ]
    },
    {
      "class_id": 119,
      "class_name": "sky-other-merged",
      "bbox": [
        0,
        0,
        511,
        224
      ]
    },
    {
      "class_id": 123,
      "class_name": "pavement-merged",
      "bbox": [
        0,
        266,
        511,
        471
      ]
    },
    {
      "class_id": 129,
      "class_name": "building-other-merged",
      "bbox": [
        411,
        201,
        511,
        249
      ]
    }
  ]
}