{
  "image": "image_208_209_heading_90.jpg",
  "class_ids": [
    2,
    91,
    100,
    116,
    117,
    119,
    123,
    125,
    129,
    131
  ],
  "class_names": [
    "car",
    "house",
    "road",
    "tree-merged",
    "fence-merged",
    "sky-other-merged",
    "pavement-merged",
    "grass-merged",
    "building-other-merged",
    "wall-other-merged"
  ],
  "regions": [
    {
      "class_id": 2,
      "class_name": "car",
      "bbox": [
        0,
        254,
        259,
        403
      ]
    },
    {
      "class_id": 91,
      "class_name": "house",
      "bbox": [
        407,
        212,
        430,
        215
      ]
    },
    {
      "class_id": 100,
      "class_name": "road",
      "bbox": [
        0,
        265,
        430,
        471
      ]
    },
    {
      "class_id": 116,
      "class_name": "tree-merged",
      "bbox": [
        235,
        159,
        511,
        378
      ]
    },
    {
      "class_id": 117,
      "class_name": "fence-merged",
      "bbox": [
        209,
        273,
        224,
        281
      ]
    },
    {
      "class_id": 119,
      "class_name": "sky-other-merged",
      "bbox": [
        0,
        0,
        459,
        245
      ]
    },
    {
      "class_id": 123,
      "class_name": "pavement-merged",
      "bbox": [
        56,
        288,
        511,
        471
      ]
    },
    {
      "class_id": 125,
      "class_name": "grass-merged",
      "bbox": [
        302,
        295,
        511,
        404
      ]
    },
    {
      "class_id": 129,
      "class_name": "building-other-merged",
      "bbox": [
        0,
        0,
        511,
        333
      ]
    },
    {
      "class_id": 131,
      "class_name": "wall-other-merged",
      "bbox": [
        0,
        153,
        261,
        332
      ]
    }
  ]
}