{
  "image": "image_881_882_heading_180.jpg",
  "class_ids": [
    0,
    2,
    11,
    100,
    116,
    119,
    123,
    125,
    129
  ],
  "class_names": [
    "person",
    "car",
    "stop sign",
    "road",
    "tree-merged",
    "sky-other-merged",
    "pavement-merged",
    "grass-merged",
    "building-other-merged"
  ],
  "regions": [
    {
      "class_id": 0,
      "class_name": "person",
      "bbox": [
        101,
        259,
        115,
        293
      ]
    },
    {
      "class_id": 2,
      "class_name": "car",
      "bbox": [
        385,
        254,
        511,
        298
      ]
    },
    {
      "class_id": 11,
      "class_name": "stop sign",
      "bbox": [
        47,
        200,
        438,
        247
      ]
    },
    {
      "class_id": 100,
      "class_name": "road",
      "bbox": [
        0,
        259,
        511,
        471
      ]
    },
    {
      "class_id": 116,
      "class_name": "tree-merged",
      "bbox": [
        0,
        180,
        511,
        294
      ]
    },
    {
      "class_id": 119,
      "class_name": "sky-other-merged",
      "bbox": [
        0,
        0,
        511,
        227
      ]
    },
    {
      "class_id": 123,
      "class_name": "pavement-merged",
      "bbox": [
        16,
        296,
        511,
        471
      ]
    },
    {
      "class_id": 125,
      "class_name": "grass-merged",
      "bbox": [
        19,
        265,
        403,
        308
      ]
    },
    {
      "class_id": 129,
      "class_name": "building-other-merged",
      "bbox": [
        216,
        44,
        511,
        266
      ]
    }
  ]
}