{
  "image": "image_725_726_heading_0.jpg",
  "class_ids": [
    0,
    2,
    7,
    100,
    116,
    117,
    119,
    123,
    129
  ],
  "class_names": [
    "person",
    "car",
    "truck",
    "road",
    "tree-merged",
    "fence-merged",
    "sky-other-merged",
    "pavement-merged",
    "building-other-merged"
  ],
  "regions": [
    {
      "class_id": 0,
      "class_name": "person",
      "bbox": [
        212,
        260,
        222,
        285
      ]
    },
    {
      "class_id": 2,
      "class_name": "car",
      "bbox": [
        127,
        256,
        216,
        293
      ]
    },
    {
      "class_id": 7,
      "class_name": "truck",
      "bbox": [
        145,
        257,
        147,
        267
      ]
    },
    {
      "class_id": 100,
      "class_name": "road",
      "bbox": [
        0,
        254,
        511,
        471
      ]
    },
    {
      "class_id": 116,
      "class_name": "tree-merged",
      "bbox": [
        0,
        230,
        511,
        333
      ]
    },
    {
      "class_id": 117,
      "class_name": "fence-merged",
      "bbox": [
        227,
        266,
        511,
        354
      ]
    },
    {
      "class_id": 119,
      "class_name": "sky-other-merged",
      "bbox": [
        32,
        0,
        319,
        258
      ]
    },
    {
      "class_id": 123,
      "class_name": "pavement-merged",
      "bbox": [
        0,
        267,
        511,
        420
      ]
    },
    {
      "class_id": 129,
      "class_name": "building-other-merged",
      "bbox": [
        0,
        0,
        511,
        272
      ]
    }
  ]
}