{
  "image": "image_831_832_heading_180.jpg",
  "class_ids": [
    106,
    116,
    117,
    119,
    123,
    125,
    126,
    129,
    131
  ],
  "class_names": [
    "stairs",
    "tree-merged",
    "fence-merged",
    "sky-other-merged",
    "pavement-merged",
    "grass-merged",
    "dirt-merged",
    "building-other-merged",
    "wall-other-merged"
  ],
  "regions": [
    {
      "class_id": 106,
      "class_name": "stairs",
      "bbox": [
        0,
        389,
        412,
        471
      ]
    },
    {
      "class_id": 116,
      "class_name": "tree-merged",
      "bbox": [
        0,
        201,
        511,
        436
      ]
    },
    {
      "class_id": 117,
      "class_name": "fence-merged",
      "bbox": [
        293,
        293,
        464,
        426
      ]
    },
    {
      "class_id": 119,
      "class_name": "sky-other-merged",
      "bbox": [
        0,
        0,
        511,
        246
      ]
    },
    {
      "class_id": 123,
      "class_name": "pavement-merged",
      "bbox": [
        352,
        374,
        511,
        471
      ]
    },
    {
      "class_id": 125,
      "class_name": "grass-merged",
      "bbox": [
        240,
        356,
        511,
        471
      ]
    },
    {
      "class_id": 126,
      "class_name": "dirt-merged",
      "bbox": [
        103,
        304,
        511,
        400
      ]
    },
    {
      "class_id": 129,
      "class_name": "building-other-merged",
      "bbox": [
        217,
        218,
        338,
        271
      ]
    },
    {
      "class_id": 131,
      "class_name": "wall-other-merged",
      "bbox": [
        224,
        269,
        511,
        321
      ]
    }
  ]
}