{
  "image": "image_104_105_heading_180.jpg",
  "class_ids": [
    2,
    3,
    7,
    86,
    91,
    100,
    115,
    117,
    119,
    123,
    129,
    131
  ],
  "class_names": [
    "car",
    "motorcycle",
    "truck",
    "door-stuff",
    "house",
    "road",
    "window-other",
    "fence-merged",
    "sky-other-merged",
    "pavement-merged",
    "building-other-merged",
    "wall-other-merged"
  ],
  "regions": [
    {
      "class_id": 2,
      "class_name": "car",
      "bbox": [
        328,
        285,
        511,
        436
      ]
    },
    {
      "class_id": 3,
      "class_name": "motorcycle",
      "bbox": [
        246,
        332,
        369,
        464
      ]
    },
    {
      "class_id": 7,
      "class_name": "truck",
      "bbox": [
        0,
        353,
        169,
        471
      ]
    },
    {
      "class_id": 86,
      "class_name": "door-stuff",
      "bbox": [
        361,
        303,
        384,
        313
      ]
    },
    {
      "class_id": 91,
      "class_name": "house",
      "bbox": [
        0,
        0,
        511,
        398
      ]
    },
    {
      "class_id": 100,
      "class_name": "road",
      "bbox": [
        166,
        358,
        511,
        471
      ]
    },
    {
      "class_id": 115,
      "class_name": "window-other",
      "bbox": [
        0,
        198,
        290,
        305
      ]
    },
    {
      "class_id": 117,
      "class_name": "fence-merged",
      "bbox": [
        0,
        0,
        139,
        75
      ]
    },
    {
      "class_id": 119,
      "class_name": "sky-other-merged",
      "bbox": [
        470,
        0,
        511,
        51
      ]
    },
    {
      "class_id": 123,
      "class_name": "pavement-merged",
      "bbox": [
        149,
        364,
        257,
        445
      ]
    },
    {
      "class_id": 129,
      "class_name": "building-other-merged",
      "bbox": [
        0,
        0,
        511,
        363
      ]
    },
    {
      "class_id": 131,
      "class_name": "wall-other-merged",
      "bbox": [
        223,
        318,
        355,
        375
      ]
    }
  ]
}