{
  "image": "image_405_406_heading_270.jpg",
  "class_ids": [
    90,
    98,
    100,
    116,
    117,
    119,
    123,
    124,
    125,
    126,
    129,
    131
  ],
  "class_names": [
    "gravel",
    "railroad",
    "road",
    "tree-merged",
    "fence-merged",
    "sky-other-merged",
    "pavement-merged",
    "mountain-merged",
    "grass-merged",
    "dirt-merged",
    "building-other-merged",
    "wall-other-merged"
  ],
  "regions": [
    {
      "class_id": 90,
      "class_name": "gravel",
      "bbox": [
        255,
        292,
        511,
        471
      ],
      "caption": "describe the gravel in the image, the road is paved and the road is paved"
    },
    {
      "class_id": 98,
      "class_name": "railroad",
      "bbox": [
        246,
        254,
        412,
        352
      ],
      "caption": "describe the railroad in the image below"
    },
    {
      "class_id": 100,
      "class_name": "road",
      "bbox": [
        0,
        245,
        450,
        471
      ],
      "caption": "describe the road in the image"
    },
    {
      "class_id": 116,
      "class_name": "tree-merged",
      "bbox": [
        0,
        0,
        511,
        279
      ],
      "caption": "describe the tree in the image"
    },
    {
      "class_id": 117,
      "class_name": "fence-merged",
      "bbox": [
        0,
        242,
        511,
        385
      ],
      "caption": "describe the fence in the image"
    },
    {
      "class_id": 119,
      "class_name": "sky-other-merged",
      "bbox": [
        21,
        0,
        511,
        251
      ],
      "caption": "describe the sky in the image"
    },
    {
      "class_id": 123,
      "class_name": "pavement-merged",
      "bbox": [
        0,
        277,
        86,
        328
      ],
      "caption": "describe the pavement in the image below"
    },
    {
      "class_id": 124,
      "class_name": "mountain-merged",
      "bbox": [
        348,
        251,
        348,
        251
      ],
      "caption": "Too small region"
    },
    {
      "class_id": 125,
      "class_name": "grass-merged",
      "bbox": [
        254,
        244,
        511,
        425
      ],
      "caption": "describe the grass in the image, the grass is green, the grass is green, the grass is green, the grass is green"
    },
    {
      "class_id": 126,
      "class_name": "dirt-merged",
      "bbox": [
        299,
        269,
        511,
        333
      ],
      "caption": "describe the dirt in the image below"
    },
    {
      "class_id": 129,
      "class_name": "building-other-merged",
      "bbox": [
        62,
        170,
        259,
        244
      ],
      "caption": "describe the building in the image below"
    },
    {
      "class_id": 131,
      "class_name": "wall-other-merged",
      "bbox": [
        0,
        253,
        121,
        302
      ],
      "caption": "describe the wall in the image below"
    }
  ]
}